Workbook

Sheet Expenses
A1: Date | B1: Category | C1: Description | D1: Amount | E1: Payment Mode | G1: Project | H1: Personal Expense Tracker
A2: 46266 | B2: Food | C2: Breakfast | D2: 60 | E2: UPI | G2: Purpose | H2: Track, analyze and visualize personal spending
A3: 46267 | B3: Transport | C3: Auto | D3: 120 | E3: Cash
A4: 46268 | B4: Shopping | C4: Clothes | D4: 1200 | E4: Card
A5: 46269 | B5: Entertainment | C5: Movie | D5: 450 | E5: UPI
A6: 46270 | B6: Bills | C6: Mobile Recharge | D6: 199 | E6: Cash
A7: 46271 | B7: Food | C7: Lunch | D7: 150 | E7: Card
A8: 46272 | B8: Transport | C8: Metro | D8: 80 | E8: UPI
A9: 46273 | B9: Shopping | C9: Cosmetics | D9: 900 | E9: Cash
A10: 46274 | B10: Entertainment | C10: Cafe | D10: 200 | E10: Card
A11: 46275 | B11: Bills | C11: Internet | D11: 599 | E11: UPI
A12: 46276 | B12: Food | C12: Dinner | D12: 220 | E12: Cash
A13: 46277 | B13: Transport | C13: Cab | D13: 350 | E13: Card
A14: 46278 | B14: Shopping | C14: Accessories | D14: 200 | E14: UPI
... A71: 46275 | B71: Bills | C71: Subscription | D71: 199 | E71: UPI

Sheet Summary
A1: PERSONAL EXPENSE TRACKER
A3: Total Spending | B3: =SUM(Expenses!D2:D71) -> 42081
A4: Average Spending | B4: =AVERAGE(Expenses!D2:D71) -> 601.15714
A5: Highest Expense | B5: =MAX(Expenses!D2:D71) -> 6000
A6: Lowest Expense | B6: =MIN(Expenses!D2:D71) -> 30
A9: CATEGORY-WISE SPENDING | D9: PAYMENT MODE ANALYSIS
A10: Category | B10: Total Spent | D10: Payment Mode | E10: Total Spent
A11: Bills | B11: =SUMIF(Expenses!B:B,A11,Expenses!D:D) -> 17491 | D11: Card | E11: =SUMIF(Expenses!E:E,D11,Expenses!D:D) -> 10017
A12: Entertainment | B12: =SUMIF(Expenses!B:B,A12,Expenses!D:D) -> 7000 | D12: Cash | E12: =SUMIF(Expenses!E:E,D12,Expenses!D:D) -> 16817
A13: Food | B13: =SUMIF(Expenses!B:B,A13,Expenses!D:D) -> 1800 | D13: UPI | E13: =SUMIF(Expenses!E:E,D13,Expenses!D:D) -> 15247
A14: Shopping | B14: =SUMIF(Expenses!B:B,A14,Expenses!D:D) -> 12750
A15: Transport | B15: =SUMIF(Expenses!B:B,A15,Expenses!D:D) -> 3040 | D15: DATE-WISE SPENDING
D16: Date | E16: Total Spent
D17: 46266 | E17: =SUMIF(Expenses!$A$2:$A$71,D17,Expenses!$D$2:$D$71) -> 390
D18: 46267 | E18: =SUMIF(Expenses!$A$2:$A$71,D18,Expenses!$D$2:$D$71) -> 440
D19: 46268 | E19: =SUMIF(Expenses!$A$2:$A$71,D19,Expenses!$D$2:$D$71) -> 2000
D20: 46269 | E20: =SUMIF(Expenses!$A$2:$A$71,D20,Expenses!$D$2:$D$71) -> 1150
D21: 46270 | E21: =SUMIF(Expenses!$A$2:$A$71,D21,Expenses!$D$2:$D$71) -> 1498
D22: 46271 | E22: =SUMIF(Expenses!$A$2:$A$71,D22,Expenses!$D$2:$D$71) -> 470
D23: 46272 | E23: =SUMIF(Expenses!$A$2:$A$71,D23,Expenses!$D$2:$D$71) -> 310
D24: 46273 | E24: =SUMIF(Expenses!$A$2:$A$71,D24,Expenses!$D$2:$D$71) -> 3250
D25: 46274 | E25: =SUMIF(Expenses!$A$2:$A$71,D25,Expenses!$D$2:$D$71) -> 1000
D26: 46275 | E26: =SUMIF(Expenses!$A$2:$A$71,D26,Expenses!$D$2:$D$71) -> 1998
D27: 46276 | E27: =SUMIF(Expenses!$A$2:$A$71,D27,Expenses!$D$2:$D$71) -> 270
D28: 46277 | E28: =SUMIF(Expenses!$A$2:$A$71,D28,Expenses!$D$2:$D$71) -> 390
... D46: 46295 | E46: =SUMIF(Expenses!$A$2:$A$71,D46,Expenses!$D$2:$D$71) -> 1048

Sheet Insights
A1: PROJECT INSIGHTS
A3: What this project shows
A5: 1. Total spending can be tracked from one place.
A6: 2. Category-wise analysis shows where most money is spent.
A7: 3. Payment mode analysis compares UPI, Cash and Card usage.
A8: 4. The daily trend chart helps identify high-spending days.
A9: 5. The summary section gives quick financial metrics.
A11: Excel skills used
A13: SUM, AVERAGE, MAX, MIN, SUMIF, charts, tables, formatting
